stable_cart/__init__.py
stable_cart/base_stable_tree.py
stable_cart/bootstrap_variance_tree.py
stable_cart/evaluation.py
stable_cart/less_greedy_tree.py
stable_cart/py.typed
stable_cart/robust_prefix.py
stable_cart/split_strategies.py
stable_cart/stability_utils.py
stable_cart/unified_bootstrap_variance_tree.py
stable_cart/unified_less_greedy_tree.py
stable_cart/unified_robust_prefix_tree.py
stable_cart-1.0.0.dist-info/WHEEL
stable_cart-1.0.0.dist-info/METADATA
stable_cart-1.0.0.dist-info/RECORD
