Metadata-Version: 2.3
Name: stable-cart
Version: 1.0.0
Summary: Unified stable CART decision trees with 7 stability primitives and cross-method learning for enhanced prediction stability.
Keywords: machine learning,decision trees,CART,stability,variance reduction,sklearn,prediction stability,bootstrap,honest learning
Author: Gaurav Sood, Arav Bhosle
Author-email: Gaurav Sood <contact@gsood.com>, Arav Bhosle <aravbhosle@gmail.com>
License: MIT License
Classifier: Development Status :: 3 - Alpha
Classifier: Intended Audience :: Science/Research
Classifier: Intended Audience :: Developers
Classifier: License :: OSI Approved :: MIT License
Classifier: Programming Language :: Python :: 3
Classifier: Programming Language :: Python :: 3.12
Classifier: Programming Language :: Python :: 3.13
Classifier: Topic :: Scientific/Engineering :: Artificial Intelligence
Classifier: Topic :: Scientific/Engineering :: Information Analysis
Classifier: Topic :: Software Development :: Libraries :: Python Modules
Classifier: Operating System :: OS Independent
Requires-Dist: numpy>=1.23.0
Requires-Dist: scikit-learn>=1.2.0
Requires-Python: >=3.12
Project-URL: Changelog, https://github.com/finite-sample/stable-cart/blob/main/CHANGELOG.md
Project-URL: Documentation, https://finite-sample.github.io/stable-cart/
Project-URL: Homepage, https://github.com/finite-sample/stable-cart
Project-URL: Issues, https://github.com/finite-sample/stable-cart/issues
Project-URL: Repository, https://github.com/finite-sample/stable-cart
